wizml/__init__.py
wizml/processor.py
wizml-0.0.12.6.dist-info/METADATA
wizml-0.0.12.6.dist-info/WHEEL
wizml-0.0.12.6.dist-info/top_level.txt
wizml-0.0.12.6.dist-info/RECORD
